{
  "modInfo": {
    "modid": "AdvancedPowerManagement",
    "name": "Advanced Power Management",
    "description": "This mod adds a Charging Bench, Battery Station, Storage Monitor, and Adjustable Transformer to Industrial Craft 2. Charge or drain up to 12 items at once, and easily automate your IC2 power generation and storage systems!",
    "version": "1.2.68-IC2-1.115",
    "url": "http://www.kaijin.com/"
  },
  "modVals": [
    {
      "name": "AdvancedPowerManagement",
      "version": "1.2.68",
      "longurl": "http://forum.industrial-craft.net/index.php?page=Thread&threadID=7900",
      "shorturl": "http://goo.gl/ly4e3",
      "aliases": "apm",
      "comment": "Beta",
      "modid": "AdvancedPowerManagement",
      "dev": ""
    }
  ]
}